phovea_security_store_generated/__init__.py
phovea_security_store_generated/api.py
phovea_security_store_generated/settings.py
phovea_security_store_generated/store.py
phovea_security_store_generated/tests/__init__.py
phovea_security_store_generated/tests/test_dummy.py
phovea_security_store_generated-13.1.0.dist-info/LICENSE
phovea_security_store_generated-13.1.0.dist-info/METADATA
phovea_security_store_generated-13.1.0.dist-info/WHEEL
phovea_security_store_generated-13.1.0.dist-info/entry_points.txt
phovea_security_store_generated-13.1.0.dist-info/top_level.txt
phovea_security_store_generated-13.1.0.dist-info/RECORD
