Metadata-Version: 2.1
Name: phovea-security-store-generated
Version: 13.1.0
Summary: UNKNOWN
Home-page: https://datavisyn.io
Author: datavisyn GmbH
Author-email: contact@datavisyn.io
License: BSD-3-Clause
Platform: UNKNOWN
Classifier: Intended Audience :: Developers
Classifier: Operating System :: OS Independent
Classifier: License :: OSI Approved :: BSD License
Classifier: Programming Language :: Python
Classifier: Programming Language :: Python :: 3.10
Requires-Python: >=3.10
License-File: LICENSE
Requires-Dist: pydng (==1.1.2)
Requires-Dist: tdp-core (<16.0.0,>=15.1.0)
Provides-Extra: develop
Requires-Dist: black (~=22.3.0) ; extra == 'develop'
Requires-Dist: debugpy (~=1.5.1) ; extra == 'develop'
Requires-Dist: flake8 (~=4.0.1) ; extra == 'develop'
Requires-Dist: isort (~=5.10.1) ; extra == 'develop'
Requires-Dist: mkdocs-material (~=8.2.8) ; extra == 'develop'
Requires-Dist: pep8-naming (~=0.12.1) ; extra == 'develop'
Requires-Dist: pytest-runner (~=6.0.0) ; extra == 'develop'
Requires-Dist: pytest (~=7.1.1) ; extra == 'develop'
Requires-Dist: recommonmark (~=0.7.1) ; extra == 'develop'
